rdfframes/__init__.py
rdfframes/knowledge_graph.py
rdfframes/client/__init__.py
rdfframes/client/client.py
rdfframes/client/http_client.py
rdfframes/client/sparql_endpoint_client.py
rdfframes/dataset/__init__.py
rdfframes/dataset/dataset.py
rdfframes/dataset/expandable_dataset.py
rdfframes/dataset/grouped_dataset.py
rdfframes/dataset/rdfpredicate.py
rdfframes/examples/__init__.py
rdfframes/examples/dblp_examples.py
rdfframes/examples/kge.py
rdfframes/examples/movie_genre_classification.py
rdfframes/query_buffer/__init__.py
rdfframes/query_buffer/query_queue.py
rdfframes/query_buffer/query_operators/__init__.py
rdfframes/query_buffer/query_operators/query_queue_operator.py
rdfframes/query_buffer/query_operators/expandable/__init__.py
rdfframes/query_buffer/query_operators/expandable/seed_operator.py
rdfframes/query_buffer/query_operators/grouped/__init__.py
rdfframes/query_buffer/query_operators/grouped/groupby_seed_operator.py
rdfframes/query_buffer/query_operators/grouped/grouped_aggregation_operator.py
rdfframes/query_buffer/query_operators/grouped/having_operator.py
rdfframes/query_buffer/query_operators/shared/__init__.py
rdfframes/query_buffer/query_operators/shared/aggregation_operator.py
rdfframes/query_buffer/query_operators/shared/expansion_operator.py
rdfframes/query_buffer/query_operators/shared/filter_operator.py
rdfframes/query_buffer/query_operators/shared/groupby_operator.py
rdfframes/query_buffer/query_operators/shared/integer_count_node.py
rdfframes/query_buffer/query_operators/shared/join_operator.py
rdfframes/query_buffer/query_operators/shared/limit_operator.py
rdfframes/query_buffer/query_operators/shared/offset_operator.py
rdfframes/query_buffer/query_operators/shared/select_operator.py
rdfframes/query_buffer/query_operators/shared/sort_operator.py
rdfframes/query_builder/__init__.py
rdfframes/query_builder/querymodel.py
rdfframes/query_builder/queue2querymodel.py
rdfframes/query_builder/sparqlbuilder.py
rdfframes/utils/__init__.py
rdfframes-0.9.3.dist-info/LICENSE
rdfframes-0.9.3.dist-info/METADATA
rdfframes-0.9.3.dist-info/WHEEL
rdfframes-0.9.3.dist-info/top_level.txt
rdfframes-0.9.3.dist-info/RECORD
