Metadata-Version: 2.1
Name: rdfframes
Version: 0.9.3
Summary: Exposes RDF datasets from sparql endpoints for machine learning models in convenient formats like pandas dataframe
Home-page: https://github.com/qcri/RDFframes
Author: Aisha Mohamed, Ghadeer Abuoda, Zoi Kaoudi, Abdurrahman Ghanem, Ashraf Aboulnaga
Author-email: ahmohamed@qf.org.qa, gabuoda@hbku.edu.qa, zkaoudi@hbku.edu.qa, abghanem@hbku.edu.qa, aaboulnaga@hbku.edu.qa
License: MIT
Platform: UNKNOWN
Classifier: License :: OSI Approved :: MIT License
Classifier: Programming Language :: Python :: 3
Classifier: Programming Language :: Python :: 3.6
